sdb/__init__.py
sdb/_version.py
sdb/command.py
sdb/error.py
sdb/mdb_compat.py
sdb/parser.py
sdb/pipeline.py
sdb/session.py
sdb/target.py
sdb/commands/__init__.py
sdb/commands/array.py
sdb/commands/container_of.py
sdb/commands/count.py
sdb/commands/echo.py
sdb/commands/exit.py
sdb/commands/filter.py
sdb/commands/head.py
sdb/commands/help.py
sdb/commands/history.py
sdb/commands/member.py
sdb/commands/pretty_print.py
sdb/commands/print.py
sdb/commands/ptype.py
sdb/commands/pyfilter.py
sdb/commands/sizeof.py
sdb/commands/sum.py
sdb/commands/tail.py
sdb/commands/type.py
sdb/commands/ustacks.py
sdb/commands/uthreads.py
sdb/commands/internal/__init__.py
sdb/commands/internal/fmt.py
sdb/commands/internal/p2.py
sdb/commands/internal/table.py
sdb/commands/internal/util.py
sdb/commands/linux/__init__.py
sdb/commands/linux/dmesg.py
sdb/commands/linux/linked_lists.py
sdb/commands/linux/per_cpu.py
sdb/commands/linux/process.py
sdb/commands/linux/slabs.py
sdb/commands/linux/stacks.py
sdb/commands/linux/threads.py
sdb/commands/linux/tree.py
sdb/commands/linux/vfs.py
sdb/commands/linux/whatis.py
sdb/commands/linux/internal/__init__.py
sdb/commands/linux/internal/slub_helpers.py
sdb/commands/spl/__init__.py
sdb/commands/spl/avl.py
sdb/commands/spl/multilist.py
sdb/commands/spl/spl_kmem_caches.py
sdb/commands/spl/spl_list.py
sdb/commands/spl/internal/__init__.py
sdb/commands/spl/internal/kmem_helpers.py
sdb/commands/zfs/__init__.py
sdb/commands/zfs/arc.py
sdb/commands/zfs/blkptr.py
sdb/commands/zfs/btree.py
sdb/commands/zfs/dbuf.py
sdb/commands/zfs/histograms.py
sdb/commands/zfs/metaslab.py
sdb/commands/zfs/range_tree.py
sdb/commands/zfs/spa.py
sdb/commands/zfs/vdev.py
sdb/commands/zfs/zfs_dbgmsg.py
sdb/commands/zfs/zio.py
sdb/commands/zfs/internal/__init__.py
sdb/internal/__init__.py
sdb/internal/cli.py
sdb/internal/repl.py
sdb_debugger-0.4.0.dist-info/licenses/LICENSE
sdb_debugger-0.4.0.dist-info/METADATA
sdb_debugger-0.4.0.dist-info/WHEEL
sdb_debugger-0.4.0.dist-info/entry_points.txt
sdb_debugger-0.4.0.dist-info/top_level.txt
sdb_debugger-0.4.0.dist-info/RECORD
