Metadata-Version: 2.4
Name: sdb-debugger
Version: 0.4.0
Summary: The Slick/Simple Debugger
Author-email: Serapheim Dimitropoulos <serapheimd@gmail.com>
License-Expression: Apache-2.0
Project-URL: Homepage, https://github.com/sdimitro/sdb
Project-URL: Repository, https://github.com/sdimitro/sdb
Project-URL: Issues, https://github.com/sdimitro/sdb/issues
Classifier: Development Status :: 5 - Production/Stable
Classifier: Environment :: Console
Classifier: Intended Audience :: Developers
Classifier: Intended Audience :: System Administrators
Classifier: Operating System :: POSIX :: Linux
Classifier: Programming Language :: Python :: 3
Classifier: Programming Language :: Python :: 3.10
Classifier: Programming Language :: Python :: 3.11
Classifier: Programming Language :: Python :: 3.12
Classifier: Topic :: Software Development :: Debuggers
Classifier: Topic :: System :: Operating System Kernels :: Linux
Requires-Python: >=3.10
License-File: LICENSE
Requires-Dist: drgn
Provides-Extra: dev
Requires-Dist: pylint; extra == "dev"
Requires-Dist: pytest; extra == "dev"
Requires-Dist: pytest-cov; extra == "dev"
Requires-Dist: mypy; extra == "dev"
Requires-Dist: yapf; extra == "dev"
Requires-Dist: ruff; extra == "dev"
Dynamic: license-file
